[
    {
        "_id": "5aa1bc45b63d79e54e7da310",
        "name": "BARBOSA",
        "department": "5aa1ac66b63d79e54e7da2d3",
        "dane_dept": "5",
        "dane_town": "05079000",
        "tcc_code": "49",
        "department_name": "ANTIOQUIA"
    },
    {
        "_id": "5aa1bc45b63d79e54e7da311",
        "name": "BELLO",
        "department": "5aa1ac66b63d79e54e7da2d3",
        "dane_dept": "5",
        "dane_town": "05088000",
        "tcc_code": "56",
        "department_name": "ANTIOQUIA"
    },
    {
        "_id": "5aa1bc45b63d79e54e7da319",
        "name": "CALDAS",
        "department": "5aa1ac66b63d79e54e7da2d3",
        "dane_dept": "5",
        "dane_town": "05129000",
        "tcc_code": "79",
        "department_name": "ANTIOQUIA"
    },
    {
        "_id": "5aa1bc45b63d79e54e7da320",
        "name": "CAUCASIA",
        "department": "5aa1ac66b63d79e54e7da2d3",
        "dane_dept": "5",
        "dane_town": "05154000",
        "tcc_code": "16",
        "department_name": "ANTIOQUIA"
    },
    {
        "_id": "5aa1bc45b63d79e54e7da322",
        "name": "CISNEROS",
        "department": "5aa1ac66b63d79e54e7da2d3",
        "dane_dept": "5",
        "dane_town": "05190000",
        "tcc_code": "119",
        "department_name": "ANTIOQUIA"
    },
    {
        "_id": "5aa1bc45b63d79e54e7da325",
        "name": "CONCEPCIÓN",
        "department": "5aa1ac66b63d79e54e7da2d3",
        "dane_dept": "5",
        "dane_town": "05206000",
        "tcc_code": "887",
        "department_name": "ANTIOQUIA"
    },
    {
        "_id": "5aa1bc45b63d79e54e7da327",
        "name": "COPACABANA",
        "department": "5aa1ac66b63d79e54e7da2d3",
        "dane_dept": "5",
        "dane_town": "05212000",
        "tcc_code": "126",
        "department_name": "ANTIOQUIA"
    },
    {
        "_id": "5aa1bc45b63d79e54e7da32c",
        "name": "EL CARMEN DE VIBORAL",
        "department": "5aa1ac66b63d79e54e7da2d3",
        "dane_dept": "5",
        "dane_town": "05148000",
        "tcc_code": "93",
        "department_name": "ANTIOQUIA"
    },
    {
        "_id": "5aa1bc45b63d79e54e7da32d",
        "name": "EL SANTUARIO",
        "department": "5aa1ac66b63d79e54e7da2d3",
        "dane_dept": "5",
        "dane_town": "05697000",
        "tcc_code": "389",
        "department_name": "ANTIOQUIA"
    },
    {
        "_id": "5aa1bc45b63d79e54e7da32f",
        "name": "ENVIGADO",
        "department": "5aa1ac66b63d79e54e7da2d3",
        "dane_dept": "5",
        "dane_town": "05266000",
        "tcc_code": "154",
        "department_name": "ANTIOQUIA"
    },
    {
        "_id": "5aa1bc45b63d79e54e7da333",
        "name": "GIRARDOTA",
        "department": "5aa1ac66b63d79e54e7da2d3",
        "dane_dept": "5",
        "dane_town": "05308000",
        "tcc_code": "180",
        "department_name": "ANTIOQUIA"
    },
    {
        "_id": "5aa1bc45b63d79e54e7da335",
        "name": "GRANADA",
        "department": "5aa1ac66b63d79e54e7da2d3",
        "dane_dept": "5",
        "dane_town": "05313000",
        "tcc_code": "183",
        "department_name": "ANTIOQUIA"
    },
    {
        "_id": "5aa1bc45b63d79e54e7da337",
        "name": "GUARNE",
        "department": "5aa1ac66b63d79e54e7da2d3",
        "dane_dept": "5",
        "dane_town": "05318000",
        "tcc_code": "193",
        "department_name": "ANTIOQUIA"
    },
    {
        "_id": "5aa1bc46b63d79e54e7da33b",
        "name": "ITAGUI",
        "department": "5aa1ac66b63d79e54e7da2d3",
        "dane_dept": "5",
        "dane_town": "05360000",
        "tcc_code": "202",
        "department_name": "ANTIOQUIA"
    },
    {
        "_id": "5aa1bc46b63d79e54e7da33f",
        "name": "LA CEJA",
        "department": "5aa1ac66b63d79e54e7da2d3",
        "dane_dept": "5",
        "dane_town": "05376000",
        "tcc_code": "207",
        "department_name": "ANTIOQUIA"
    },
    {
        "_id": "5aa1bc46b63d79e54e7da340",
        "name": "LA ESTRELLA",
        "department": "5aa1ac66b63d79e54e7da2d3",
        "dane_dept": "5",
        "dane_town": "05380000",
        "tcc_code": "211",
        "department_name": "ANTIOQUIA"
    },
    {
        "_id": "5aa1bc46b63d79e54e7da342",
        "name": "LA UNIÓN",
        "department": "5aa1ac66b63d79e54e7da2d3",
        "dane_dept": "5",
        "dane_town": "05400000",
        "tcc_code": "226",
        "department_name": "ANTIOQUIA"
    },
    {
        "_id": "5aa1bc46b63d79e54e7da345",
        "name": "MARINILLA",
        "department": "5aa1ac66b63d79e54e7da2d3",
        "dane_dept": "5",
        "dane_town": "05440000",
        "tcc_code": "248",
        "department_name": "ANTIOQUIA"
    },
    {
        "_id": "5aa1bc46b63d79e54e7da346",
        "name": "MEDELLÍN",
        "department": "5aa1ac66b63d79e54e7da2d3",
        "dane_dept": "5",
        "dane_town": "05001000",
        "tcc_code": "1",
        "department_name": "ANTIOQUIA"
    },
    {
        "_id": "5aa1bc46b63d79e54e7da347",
        "name": "MONTEBELLO",
        "department": "5aa1ac66b63d79e54e7da2d3",
        "dane_dept": "5",
        "dane_town": "05467000",
        "tcc_code": "722",
        "department_name": "ANTIOQUIA"
    },
    {
        "_id": "5aa1bc46b63d79e54e7da355",
        "name": "RETIRO",
        "department": "5aa1ac66b63d79e54e7da2d3",
        "dane_dept": "5",
        "dane_town": "05607000",
        "tcc_code": "152",
        "department_name": "ANTIOQUIA"
    },
    {
        "_id": "5aa1bc46b63d79e54e7da356",
        "name": "RIONEGRO",
        "department": "5aa1ac66b63d79e54e7da2d3",
        "dane_dept": "5",
        "dane_town": "05615000",
        "tcc_code": "327",
        "department_name": "ANTIOQUIA"
    },
    {
        "_id": "5aa1bc46b63d79e54e7da358",
        "name": "SABANETA",
        "department": "5aa1ac66b63d79e54e7da2d3",
        "dane_dept": "5",
        "dane_town": "05631000",
        "tcc_code": "339",
        "department_name": "ANTIOQUIA"
    },
    {
        "_id": "5aa1bc46b63d79e54e7da37e",
        "name": "ZARAGOZA",
        "department": "5aa1ac66b63d79e54e7da2d3",
        "dane_dept": "5",
        "dane_town": "05895000",
        "tcc_code": "462",
        "department_name": "ANTIOQUIA"
    },
    {
        "_id": "5aa1bc47b63d79e54e7da389",
        "name": "BARRANQUILLA",
        "department": "5aa1ac66b63d79e54e7da2d6",
        "dane_dept": "8",
        "dane_town": "08001000",
        "tcc_code": "7",
        "department_name": "ATLÁNTICO"
    },
    {
        "_id": "5aa1bc47b63d79e54e7da38b",
        "name": "CANDELARIA",
        "department": "5aa1ac66b63d79e54e7da2d6",
        "dane_dept": "8",
        "dane_town": "08141000",
        "tcc_code": "786",
        "department_name": "ATLÁNTICO"
    },
    {
        "_id": "5aa1bc47b63d79e54e7da38f",
        "name": "MALAMBO",
        "department": "5aa1ac66b63d79e54e7da2d6",
        "dane_dept": "08",
        "dane_town": "08433000",
        "tcc_code": "243",
        "department_name": "ATLÁNTICO"
    },
    {
        "_id": "5aa1bc47b63d79e54e7da39b",
        "name": "SOLEDAD",
        "department": "5aa1ac66b63d79e54e7da2d6",
        "dane_dept": "08",
        "dane_town": "08758000",
        "tcc_code": "403",
        "department_name": "ATLÁNTICO"
    },
    {
        "_id": "5aa1bc47b63d79e54e7da39f",
        "name": "BOGOTÁ D.C.",
        "department": "5aa1ac66b63d79e54e7da2d7",
        "dane_dept": "11",
        "dane_town": "11001000",
        "tcc_code": "4",
        "department_name": "BOGOTÁ D.C."
    },
    {
        "_id": "5aa1bc47b63d79e54e7da3a3",
        "name": "ARJONA",
        "department": "5aa1ac66b63d79e54e7da2d8",
        "dane_dept": "13",
        "dane_town": "13052000",
        "tcc_code": "39",
        "department_name": "BOLÍVAR"
    },
    {
        "_id": "5aa1bc47b63d79e54e7da3a8",
        "name": "CARTAGENA",
        "department": "5aa1ac66b63d79e54e7da2d8",
        "dane_dept": "13",
        "dane_town": "13001000",
        "tcc_code": "10",
        "department_name": "BOLÍVAR"
    },
    {
        "_id": "5aa1bc47b63d79e54e7da3aa",
        "name": "CLEMENCIA",
        "department": "5aa1ac66b63d79e54e7da2d8",
        "dane_dept": "13",
        "dane_town": "13222000",
        "tcc_code": "1092",
        "department_name": "BOLÍVAR"
    },
    {
        "_id": "5aa1bc47b63d79e54e7da3ac",
        "name": "EL CARMEN DE BOLÍVAR",
        "department": "5aa1ac66b63d79e54e7da2d8",
        "dane_dept": "13",
        "dane_town": "13244000",
        "tcc_code": "91",
        "department_name": "BOLÍVAR"
    },
    {
        "_id": "5aa1bc47b63d79e54e7da3b0",
        "name": "MAGANGUÉ",
        "department": "5aa1ac66b63d79e54e7da2d8",
        "dane_dept": "13",
        "dane_town": "13430000",
        "tcc_code": "240",
        "department_name": "BOLÍVAR"
    },
    {
        "_id": "5aa1bc47b63d79e54e7da3b1",
        "name": "MAHATES",
        "department": "5aa1ac66b63d79e54e7da2d8",
        "dane_dept": "13",
        "dane_town": "13433000",
        "tcc_code": "678",
        "department_name": "BOLÍVAR"
    },
    {
        "_id": "5aa1bc47b63d79e54e7da3b3",
        "name": "MARÍA LA BAJA",
        "department": "5aa1ac66b63d79e54e7da2d8",
        "dane_dept": "13",
        "dane_town": "13442000",
        "tcc_code": "247",
        "department_name": "BOLÍVAR"
    },
    {
        "_id": "5aa1bc47b63d79e54e7da3bc",
        "name": "SAN ESTANISLAO",
        "department": "5aa1ac66b63d79e54e7da2d8",
        "dane_dept": "13",
        "dane_town": "13647000",
        "tcc_code": "24540",
        "department_name": "BOLÍVAR"
    },
    {
        "_id": "5aa1bc47b63d79e54e7da3be",
        "name": "SAN JACINTO",
        "department": "5aa1ac66b63d79e54e7da2d8",
        "dane_dept": "13",
        "dane_town": "13654000",
        "tcc_code": "359",
        "department_name": "BOLÍVAR"
    },
    {
        "_id": "5aa1bc47b63d79e54e7da3c0",
        "name": "SAN JUAN NEPOMUCENO",
        "department": "5aa1ac66b63d79e54e7da2d8",
        "dane_dept": "13",
        "dane_town": "13657000",
        "tcc_code": "364",
        "department_name": "BOLÍVAR"
    },
    {
        "_id": "5aa1bc47b63d79e54e7da3c3",
        "name": "SANTA CATALINA",
        "department": "5aa1ac66b63d79e54e7da2d8",
        "dane_dept": "13",
        "dane_town": "13673000",
        "tcc_code": "635",
        "department_name": "BOLÍVAR"
    },
    {
        "_id": "5aa1bc47b63d79e54e7da3c7",
        "name": "SOPLAVIENTO",
        "department": "5aa1ac66b63d79e54e7da2d8",
        "dane_dept": "13",
        "dane_town": "13760000",
        "tcc_code": "1199",
        "department_name": "BOLÍVAR"
    },
    {
        "_id": "5aa1bc47b63d79e54e7da3ca",
        "name": "TURBACO",
        "department": "5aa1ac66b63d79e54e7da2d8",
        "dane_dept": "13",
        "dane_town": "13836000",
        "tcc_code": "431",
        "department_name": "BOLÍVAR"
    },
    {
        "_id": "5aa1bc47b63d79e54e7da3cb",
        "name": "TURBANÁ",
        "department": "5aa1ac66b63d79e54e7da2d8",
        "dane_dept": "13",
        "dane_town": "13838000",
        "tcc_code": "757",
        "department_name": "BOLÍVAR"
    },
    {
        "_id": "5aa1bc47b63d79e54e7da3cc",
        "name": "VILLANUEVA",
        "department": "5aa1ac66b63d79e54e7da2d8",
        "dane_dept": "13",
        "dane_town": "13873000",
        "tcc_code": "811",
        "department_name": "BOLÍVAR"
    },
    {
        "_id": "5aa1bc48b63d79e54e7da3cf",
        "name": "AQUITANIA",
        "department": "5aa1ac66b63d79e54e7da2d9",
        "dane_dept": "15",
        "dane_town": "15047000",
        "tcc_code": "676",
        "department_name": "BOYACÁ"
    },
    {
        "_id": "5aa1bc48b63d79e54e7da3d0",
        "name": "ARCABUCO",
        "department": "5aa1ac66b63d79e54e7da2d9",
        "dane_dept": "15",
        "dane_town": "15051000",
        "tcc_code": "599",
        "department_name": "BOYACÁ"
    },
    {
        "_id": "5aa1bc48b63d79e54e7da3d3",
        "name": "BETÉITIVA",
        "department": "5aa1ac66b63d79e54e7da2d9",
        "dane_dept": "15",
        "dane_town": "15092000",
        "tcc_code": "1660",
        "department_name": "BOYACÁ"
    },
    {
        "_id": "5aa1bc48b63d79e54e7da3d8",
        "name": "BUSBANZÁ",
        "department": "5aa1ac66b63d79e54e7da2d9",
        "dane_dept": "15",
        "dane_town": "15114000",
        "tcc_code": "1661",
        "department_name": "BOYACÁ"
    },
    {
        "_id": "5aa1bc48b63d79e54e7da3dd",
        "name": "CHIQUINQUIRÁ",
        "department": "5aa1ac66b63d79e54e7da2d9",
        "dane_dept": "15",
        "dane_town": "15176000",
        "tcc_code": "111",
        "department_name": "BOYACÁ"
    },
    {
        "_id": "5aa1bc48b63d79e54e7da3e7",
        "name": "CORRALES",
        "department": "5aa1ac66b63d79e54e7da2d9",
        "dane_dept": "15",
        "dane_town": "15215000",
        "tcc_code": "1668",
        "department_name": "BOYACÁ"
    },
    {
        "_id": "5aa1bc48b63d79e54e7da3eb",
        "name": "CUÍTIVA",
        "department": "5aa1ac66b63d79e54e7da2d9",
        "dane_dept": "15",
        "dane_town": "15226000",
        "tcc_code": "1670",
        "department_name": "BOYACÁ"
    },
    {
        "_id": "5aa1bc48b63d79e54e7da3ec",
        "name": "DUITAMA",
        "department": "5aa1ac66b63d79e54e7da2d9",
        "dane_dept": "15",
        "dane_town": "15238000",
        "tcc_code": "141",
        "department_name": "BOYACÁ"
    },
    {
        "_id": "5aa1bc48b63d79e54e7da3ef",
        "name": "FIRAVITOBA",
        "department": "5aa1ac66b63d79e54e7da2d9",
        "dane_dept": "15",
        "dane_town": "15272000",
        "tcc_code": "1125",
        "department_name": "BOYACÁ"
    },
    {
        "_id": "5aa1bc48b63d79e54e7da3f0",
        "name": "FLORESTA",
        "department": "5aa1ac66b63d79e54e7da2d9",
        "dane_dept": "15",
        "dane_town": "15276000",
        "tcc_code": "730",
        "department_name": "BOYACÁ"
    },
    {
        "_id": "5aa1bc48b63d79e54e7da3f2",
        "name": "GAMEZA",
        "department": "5aa1ac66b63d79e54e7da2d9",
        "dane_dept": "15",
        "dane_town": "15296000",
        "tcc_code": "689",
        "department_name": "BOYACÁ"
    },
    {
        "_id": "5aa1bc48b63d79e54e7da3f8",
        "name": "IZA",
        "department": "5aa1ac66b63d79e54e7da2d9",
        "dane_dept": "15",
        "dane_town": "15362000",
        "tcc_code": "1674",
        "department_name": "BOYACÁ"
    },
    {
        "_id": "5aa1bc48b63d79e54e7da402",
        "name": "MONGUA",
        "department": "5aa1ac66b63d79e54e7da2d9",
        "dane_dept": "15",
        "dane_town": "15464000",
        "tcc_code": "1126",
        "department_name": "BOYACÁ"
    },
    {
        "_id": "5aa1bc48b63d79e54e7da403",
        "name": "MONGUÍ",
        "department": "5aa1ac66b63d79e54e7da2d9",
        "dane_dept": "15",
        "dane_town": "15466000",
        "tcc_code": "714",
        "department_name": "BOYACÁ"
    },
    {
        "_id": "5aa1bc48b63d79e54e7da404",
        "name": "MONIQUIRÁ",
        "department": "5aa1ac66b63d79e54e7da2d9",
        "dane_dept": "15",
        "dane_town": "15469000",
        "tcc_code": "256",
        "department_name": "BOYACÁ"
    },
    {
        "_id": "5aa1bc48b63d79e54e7da407",
        "name": "NOBSA",
        "department": "5aa1ac66b63d79e54e7da2d9",
        "dane_dept": "15",
        "dane_town": "15491000",
        "tcc_code": "267",
        "department_name": "BOYACÁ"
    },
    {
        "_id": "5aa1bc48b63d79e54e7da40d",
        "name": "PAIPA",
        "department": "5aa1ac66b63d79e54e7da2d9",
        "dane_dept": "15",
        "dane_town": "15516000",
        "tcc_code": "277",
        "department_name": "BOYACÁ"
    },
    {
        "_id": "5aa1bc48b63d79e54e7da40e",
        "name": "PAJARITO",
        "department": "5aa1ac66b63d79e54e7da2d9",
        "dane_dept": "15",
        "dane_town": "15518000",
        "tcc_code": "1050",
        "department_name": "BOYACÁ"
    },
    {
        "_id": "5aa1bc48b63d79e54e7da413",
        "name": "PESCA",
        "department": "5aa1ac66b63d79e54e7da2d9",
        "dane_dept": "15",
        "dane_town": "15542000",
        "tcc_code": "572",
        "department_name": "BOYACÁ"
    },
    {
        "_id": "5aa1bc48b63d79e54e7da418",
        "name": "RÁQUIRA",
        "department": "5aa1ac66b63d79e54e7da2d9",
        "dane_dept": "15",
        "dane_town": "15600000",
        "tcc_code": "1082",
        "department_name": "BOYACÁ"
    },
    {
        "_id": "5aa1bc49b63d79e54e7da41b",
        "name": "SÁCHICA",
        "department": "5aa1ac66b63d79e54e7da2d9",
        "dane_dept": "15",
        "dane_town": "15638000",
        "tcc_code": "884",
        "department_name": "BOYACÁ"
    },
    {
        "_id": "5aa1bc49b63d79e54e7da41c",
        "name": "SAMACÁ",
        "department": "5aa1ac66b63d79e54e7da2d9",
        "dane_dept": "15",
        "dane_town": "15646000",
        "tcc_code": "547",
        "department_name": "BOYACÁ"
    },
    {
        "_id": "5aa1bc49b63d79e54e7da42d",
        "name": "SOGAMOSO",
        "department": "5aa1ac66b63d79e54e7da2d9",
        "dane_dept": "15",
        "dane_town": "15759000",
        "tcc_code": "402",
        "department_name": "BOYACÁ"
    },
    {
        "_id": "5aa1bc49b63d79e54e7da430",
        "name": "SORACÁ",
        "department": "5aa1ac66b63d79e54e7da2d9",
        "dane_dept": "15",
        "dane_town": "15764000",
        "tcc_code": "1693",
        "department_name": "BOYACÁ"
    },
    {
        "_id": "5aa1bc49b63d79e54e7da433",
        "name": "SUTAMARCHÁN",
        "department": "5aa1ac66b63d79e54e7da2d9",
        "dane_dept": "15",
        "dane_town": "15776000",
        "tcc_code": "816",
        "department_name": "BOYACÁ"
    },
    {
        "_id": "5aa1bc49b63d79e54e7da435",
        "name": "TASCO",
        "department": "5aa1ac66b63d79e54e7da2d9",
        "dane_dept": "15",
        "dane_town": "15790000",
        "tcc_code": "1080",
        "department_name": "BOYACÁ"
    },
    {
        "_id": "5aa1bc49b63d79e54e7da438",
        "name": "TIBASOSA",
        "department": "5aa1ac66b63d79e54e7da2d9",
        "dane_dept": "15",
        "dane_town": "15806000",
        "tcc_code": "550",
        "department_name": "BOYACÁ"
    },
    {
        "_id": "5aa1bc49b63d79e54e7da439",
        "name": "TINJACÁ",
        "department": "5aa1ac66b63d79e54e7da2d9",
        "dane_dept": "15",
        "dane_town": "15808000",
        "tcc_code": "882",
        "department_name": "BOYACÁ"
    },
    {
        "_id": "5aa1bc49b63d79e54e7da43d",
        "name": "TÓPAGA",
        "department": "5aa1ac66b63d79e54e7da2d9",
        "dane_dept": "15",
        "dane_town": "15820000",
        "tcc_code": "1696",
        "department_name": "BOYACÁ"
    },
    {
        "_id": "5aa1bc49b63d79e54e7da43e",
        "name": "TOTA",
        "department": "5aa1ac66b63d79e54e7da2d9",
        "dane_dept": "15",
        "dane_town": "15822000",
        "tcc_code": "1697",
        "department_name": "BOYACÁ"
    },
    {
        "_id": "5aa1bc49b63d79e54e7da43f",
        "name": "TUNJA",
        "department": "5aa1ac66b63d79e54e7da2d9",
        "dane_dept": "15",
        "dane_town": "15001000",
        "tcc_code": "20",
        "department_name": "BOYACÁ"
    },
    {
        "_id": "5aa1bc49b63d79e54e7da445",
        "name": "VENTAQUEMADA",
        "department": "5aa1ac66b63d79e54e7da2d9",
        "dane_dept": "15",
        "dane_town": "15861000",
        "tcc_code": "442",
        "department_name": "BOYACÁ"
    },
    {
        "_id": "5aa1bc49b63d79e54e7da446",
        "name": "VILLA DE LEYVA",
        "department": "5aa1ac66b63d79e54e7da2d9",
        "dane_dept": "15",
        "dane_town": "15407000",
        "tcc_code": "476",
        "department_name": "BOYACÁ"
    },
    {
        "_id": "5aa1bc49b63d79e54e7da451",
        "name": "MANIZALES",
        "department": "5aa1ac66b63d79e54e7da2da",
        "dane_dept": "17",
        "dane_town": "17001000",
        "tcc_code": "8",
        "department_name": "CALDAS"
    },
    {
        "_id": "5aa1bc4ab63d79e54e7da462",
        "name": "VILLAMARÍA",
        "department": "5aa1ac66b63d79e54e7da2da",
        "dane_dept": "17",
        "dane_town": "17873000",
        "tcc_code": "448",
        "department_name": "CALDAS"
    },
    {
        "_id": "5aa1bc4ab63d79e54e7da474",
        "name": "AGUAZUL",
        "department": "5aa1ac66b63d79e54e7da2dc",
        "dane_dept": "85",
        "dane_town": "85010000",
        "tcc_code": "609",
        "department_name": "CASANARE"
    },
    {
        "_id": "5aa1bc4ab63d79e54e7da486",
        "name": "YOPAL",
        "department": "5aa1ac66b63d79e54e7da2dc",
        "dane_dept": "85",
        "dane_town": "85001000",
        "tcc_code": "458",
        "department_name": "CASANARE"
    },
    {
        "_id": "5aa1bc4ab63d79e54e7da48b",
        "name": "BUENOS AIRES",
        "department": "5aa1ac66b63d79e54e7da2dd",
        "dane_dept": "19",
        "dane_town": "19110000",
        "tcc_code": "658",
        "department_name": "CAUCA"
    },
    {
        "_id": "5aa1bc4ab63d79e54e7da48e",
        "name": "CALOTO",
        "department": "5aa1ac66b63d79e54e7da2dd",
        "dane_dept": "19",
        "dane_town": "19142000",
        "tcc_code": "577",
        "department_name": "CAUCA"
    },
    {
        "_id": "5aa1bc4ab63d79e54e7da48f",
        "name": "CORINTO",
        "department": "5aa1ac66b63d79e54e7da2dd",
        "dane_dept": "19",
        "dane_town": "19212000",
        "tcc_code": "128",
        "department_name": "CAUCA"
    },
    {
        "_id": "5aa1bc4ab63d79e54e7da497",
        "name": "LA VEGA",
        "department": "5aa1ac66b63d79e54e7da2dd",
        "dane_dept": "19",
        "dane_town": "19397000",
        "tcc_code": "759",
        "department_name": "CAUCA"
    },
    {
        "_id": "5aa1bc4ab63d79e54e7da49a",
        "name": "MIRANDA",
        "department": "5aa1ac66b63d79e54e7da2dd",
        "dane_dept": "19",
        "dane_town": "19455000",
        "tcc_code": "666",
        "department_name": "CAUCA"
    },
    {
        "_id": "5aa1bc4ab63d79e54e7da49c",
        "name": "PADILLA",
        "department": "5aa1ac66b63d79e54e7da2dd",
        "dane_dept": "19",
        "dane_town": "19513000",
        "tcc_code": "742",
        "department_name": "CAUCA"
    },
    {
        "_id": "5aa1bc4ab63d79e54e7da4a1",
        "name": "POPAYÁN",
        "department": "5aa1ac66b63d79e54e7da2dd",
        "dane_dept": "19",
        "dane_town": "19001000",
        "tcc_code": "294",
        "department_name": "CAUCA"
    },
    {
        "_id": "5aa1bc4bb63d79e54e7da4a2",
        "name": "PUERTO TEJADA",
        "department": "5aa1ac66b63d79e54e7da2dd",
        "dane_dept": "19",
        "dane_town": "19573000",
        "tcc_code": "310",
        "department_name": "CAUCA"
    },
    {
        "_id": "5aa1bc4bb63d79e54e7da4aa",
        "name": "SUÁREZ",
        "department": "5aa1ac66b63d79e54e7da2dd",
        "dane_dept": "19",
        "dane_town": "19780000",
        "tcc_code": "661",
        "department_name": "CAUCA"
    },
    {
        "_id": "5aa1bc4bb63d79e54e7da4b0",
        "name": "VILLA RICA",
        "department": "5aa1ac66b63d79e54e7da2dd",
        "dane_dept": "19",
        "dane_town": "19845000",
        "tcc_code": "1154",
        "department_name": "CAUCA"
    },
    {
        "_id": "5aa1bc4bb63d79e54e7da4b5",
        "name": "BOSCONIA",
        "department": "5aa1ac66b63d79e54e7da2de",
        "dane_dept": "20",
        "dane_town": "20060000",
        "tcc_code": "67",
        "department_name": "CESAR"
    },
    {
        "_id": "5aa1bc4bb63d79e54e7da4b9",
        "name": "EL COPEY",
        "department": "5aa1ac66b63d79e54e7da2de",
        "dane_dept": "20",
        "dane_town": "20238000",
        "tcc_code": "148",
        "department_name": "CESAR"
    },
    {
        "_id": "5aa1bc4bb63d79e54e7da4c7",
        "name": "SAN MARTÍN",
        "department": "5aa1ac66b63d79e54e7da2de",
        "dane_dept": "20",
        "dane_town": "20770000",
        "tcc_code": "368",
        "department_name": "CESAR"
    },
    {
        "_id": "5aa1bc4bb63d79e54e7da4c9",
        "name": "VALLEDUPAR",
        "department": "5aa1ac66b63d79e54e7da2de",
        "dane_dept": "20",
        "dane_town": "20001000",
        "tcc_code": "438",
        "department_name": "CESAR"
    },
    {
        "_id": "5aa1bc4cb63d79e54e7da4ec",
        "name": "CERETÉ",
        "department": "5aa1ac66b63d79e54e7da2e0",
        "dane_dept": "23",
        "dane_town": "23162000",
        "tcc_code": "98",
        "department_name": "CÓRDOBA"
    },
    {
        "_id": "5aa1bc4cb63d79e54e7da4ee",
        "name": "CHINÚ",
        "department": "5aa1ac66b63d79e54e7da2e0",
        "dane_dept": "23",
        "dane_town": "23182000",
        "tcc_code": "110",
        "department_name": "CÓRDOBA"
    },
    {
        "_id": "5aa1bc4cb63d79e54e7da4ef",
        "name": "CIÉNAGA DE ORO",
        "department": "5aa1ac66b63d79e54e7da2e0",
        "dane_dept": "23",
        "dane_town": "23189000",
        "tcc_code": "115",
        "department_name": "CÓRDOBA"
    },
    {
        "_id": "5aa1bc4cb63d79e54e7da4f6",
        "name": "MONTERÍA",
        "department": "5aa1ac66b63d79e54e7da2e0",
        "dane_dept": "23",
        "dane_town": "23001000",
        "tcc_code": "15",
        "department_name": "CÓRDOBA"
    },
    {
        "_id": "5aa1bc4cb63d79e54e7da4fd",
        "name": "SAHAGÚN",
        "department": "5aa1ac66b63d79e54e7da2e0",
        "dane_dept": "23",
        "dane_town": "23660000",
        "tcc_code": "340",
        "department_name": "CÓRDOBA"
    },
    {
        "_id": "5aa1bc4cb63d79e54e7da4ff",
        "name": "SAN ANTERO",
        "department": "5aa1ac66b63d79e54e7da2e0",
        "dane_dept": "23",
        "dane_town": "23672000",
        "tcc_code": "628",
        "department_name": "CÓRDOBA"
    },
    {
        "_id": "5aa1bc4cb63d79e54e7da507",
        "name": "AGUA DE DIOS",
        "department": "5aa1ac66b63d79e54e7da2e1",
        "dane_dept": "25",
        "dane_town": "25001000",
        "tcc_code": "734",
        "department_name": "CUNDINAMARCA"
    },
    {
        "_id": "5aa1bc4cb63d79e54e7da508",
        "name": "ALBÁN",
        "department": "5aa1ac66b63d79e54e7da2e1",
        "dane_dept": "25",
        "dane_town": "25019000",
        "tcc_code": "912",
        "department_name": "CUNDINAMARCA"
    },
    {
        "_id": "5aa1bc4cb63d79e54e7da509",
        "name": "ANAPOIMA",
        "department": "5aa1ac66b63d79e54e7da2e1",
        "dane_dept": "25",
        "dane_town": "25035000",
        "tcc_code": "27",
        "department_name": "CUNDINAMARCA"
    },
    {
        "_id": "5aa1bc4cb63d79e54e7da50a",
        "name": "ANOLAIMA",
        "department": "5aa1ac66b63d79e54e7da2e1",
        "dane_dept": "25",
        "dane_town": "25040000",
        "tcc_code": "30",
        "department_name": "CUNDINAMARCA"
    },
    {
        "_id": "5aa1bc4cb63d79e54e7da50b",
        "name": "APULO",
        "department": "5aa1ac66b63d79e54e7da2e1",
        "dane_dept": "25",
        "dane_town": "25599000",
        "tcc_code": "604",
        "department_name": "CUNDINAMARCA"
    },
    {
        "_id": "5aa1bc4cb63d79e54e7da50c",
        "name": "ARBELÁEZ",
        "department": "5aa1ac66b63d79e54e7da2e1",
        "dane_dept": "25",
        "dane_town": "25053000",
        "tcc_code": "512",
        "department_name": "CUNDINAMARCA"
    },
    {
        "_id": "5aa1bc4cb63d79e54e7da50f",
        "name": "BOJACÁ",
        "department": "5aa1ac66b63d79e54e7da2e1",
        "dane_dept": "25",
        "dane_town": "25099000",
        "tcc_code": "60",
        "department_name": "CUNDINAMARCA"
    },
    {
        "_id": "5aa1bc4cb63d79e54e7da511",
        "name": "CACHIPAY",
        "department": "5aa1ac66b63d79e54e7da2e1",
        "dane_dept": "25",
        "dane_town": "25123000",
        "tcc_code": "611",
        "department_name": "CUNDINAMARCA"
    },
    {
        "_id": "5aa1bc4cb63d79e54e7da512",
        "name": "CAJICÁ",
        "department": "5aa1ac66b63d79e54e7da2e1",
        "dane_dept": "25",
        "dane_town": "25126000",
        "tcc_code": "76",
        "department_name": "CUNDINAMARCA"
    },
    {
        "_id": "5aa1bc4cb63d79e54e7da515",
        "name": "CARMEN DE CARUPA",
        "department": "5aa1ac66b63d79e54e7da2e1",
        "dane_dept": "25",
        "dane_town": "25154000",
        "tcc_code": "92",
        "department_name": "CUNDINAMARCA"
    },
    {
        "_id": "5aa1bc4cb63d79e54e7da517",
        "name": "CHÍA",
        "department": "5aa1ac66b63d79e54e7da2e1",
        "dane_dept": "25",
        "dane_town": "25175000",
        "tcc_code": "104",
        "department_name": "CUNDINAMARCA"
    },
    {
        "_id": "5aa1bc4cb63d79e54e7da51a",
        "name": "CHOCONTÁ",
        "department": "5aa1ac66b63d79e54e7da2e1",
        "dane_dept": "25",
        "dane_town": "25183000",
        "tcc_code": "114",
        "department_name": "CUNDINAMARCA"
    },
    {
        "_id": "5aa1bc4cb63d79e54e7da51b",
        "name": "COGUA",
        "department": "5aa1ac66b63d79e54e7da2e1",
        "dane_dept": "25",
        "dane_town": "25200000",
        "tcc_code": "726",
        "department_name": "CUNDINAMARCA"
    },
    {
        "_id": "5aa1bc4cb63d79e54e7da51d",
        "name": "CUCUNUBÁ",
        "department": "5aa1ac66b63d79e54e7da2e1",
        "dane_dept": "25",
        "dane_town": "25224000",
        "tcc_code": "1669",
        "department_name": "CUNDINAMARCA"
    },
    {
        "_id": "5aa1bc4db63d79e54e7da51e",
        "name": "EL COLEGIO",
        "department": "5aa1ac66b63d79e54e7da2e1",
        "dane_dept": "25",
        "dane_town": "25245000",
        "tcc_code": "253",
        "department_name": "CUNDINAMARCA"
    },
    {
        "_id": "5aa1bc4db63d79e54e7da520",
        "name": "EL ROSAL",
        "department": "5aa1ac66b63d79e54e7da2e1",
        "dane_dept": "25",
        "dane_town": "25260000",
        "tcc_code": "729",
        "department_name": "CUNDINAMARCA"
    },
    {
        "_id": "5aa1bc4db63d79e54e7da521",
        "name": "FACATATIVÁ",
        "department": "5aa1ac66b63d79e54e7da2e1",
        "dane_dept": "25",
        "dane_town": "25269000",
        "tcc_code": "156",
        "department_name": "CUNDINAMARCA"
    },
    {
        "_id": "5aa1bc4db63d79e54e7da524",
        "name": "FUNZA",
        "department": "5aa1ac66b63d79e54e7da2e1",
        "dane_dept": "25",
        "dane_town": "25286000",
        "tcc_code": "170",
        "department_name": "CUNDINAMARCA"
    },
    {
        "_id": "5aa1bc4db63d79e54e7da525",
        "name": "FÚQUENE",
        "department": "5aa1ac66b63d79e54e7da2e1",
        "dane_dept": "25",
        "dane_town": "25288000",
        "tcc_code": "1672",
        "department_name": "CUNDINAMARCA"
    },
    {
        "_id": "5aa1bc4db63d79e54e7da526",
        "name": "FUSAGASUGÁ",
        "department": "5aa1ac66b63d79e54e7da2e1",
        "dane_dept": "25",
        "dane_town": "25290000",
        "tcc_code": "171",
        "department_name": "CUNDINAMARCA"
    },
    {
        "_id": "5aa1bc4db63d79e54e7da528",
        "name": "GACHANCIPÁ",
        "department": "5aa1ac66b63d79e54e7da2e1",
        "dane_dept": "25",
        "dane_town": "25295000",
        "tcc_code": "493",
        "department_name": "CUNDINAMARCA"
    },
    {
        "_id": "5aa1bc4db63d79e54e7da52d",
        "name": "GUACHETÁ",
        "department": "5aa1ac66b63d79e54e7da2e1",
        "dane_dept": "25",
        "dane_town": "25317000",
        "tcc_code": "645",
        "department_name": "CUNDINAMARCA"
    },
    {
        "_id": "5aa1bc4db63d79e54e7da52e",
        "name": "GUADUAS",
        "department": "5aa1ac66b63d79e54e7da2e1",
        "dane_dept": "25",
        "dane_town": "25320000",
        "tcc_code": "187",
        "department_name": "CUNDINAMARCA"
    },
    {
        "_id": "5aa1bc4db63d79e54e7da537",
        "name": "LA CALERA",
        "department": "5aa1ac66b63d79e54e7da2e1",
        "dane_dept": "25",
        "dane_town": "25377000",
        "tcc_code": "466",
        "department_name": "CUNDINAMARCA"
    },
    {
        "_id": "5aa1bc4db63d79e54e7da538",
        "name": "LA MESA",
        "department": "5aa1ac66b63d79e54e7da2e1",
        "dane_dept": "25",
        "dane_town": "25386000",
        "tcc_code": "215",
        "department_name": "CUNDINAMARCA"
    },
    {
        "_id": "5aa1bc4db63d79e54e7da53c",
        "name": "LENGUAZAQUE",
        "department": "5aa1ac66b63d79e54e7da2e1",
        "dane_dept": "25",
        "dane_town": "25407000",
        "tcc_code": "901",
        "department_name": "CUNDINAMARCA"
    },
    {
        "_id": "5aa1bc4db63d79e54e7da53e",
        "name": "MADRID",
        "department": "5aa1ac66b63d79e54e7da2e1",
        "dane_dept": "25",
        "dane_town": "25430000",
        "tcc_code": "239",
        "department_name": "CUNDINAMARCA"
    },
    {
        "_id": "5aa1bc4db63d79e54e7da541",
        "name": "MOSQUERA",
        "department": "5aa1ac66b63d79e54e7da2e1",
        "dane_dept": "25",
        "dane_town": "25473000",
        "tcc_code": "260",
        "department_name": "CUNDINAMARCA"
    },
    {
        "_id": "5aa1bc4db63d79e54e7da543",
        "name": "NEMOCÓN",
        "department": "5aa1ac66b63d79e54e7da2e1",
        "dane_dept": "25",
        "dane_town": "25486000",
        "tcc_code": "700",
        "department_name": "CUNDINAMARCA"
    },
    {
        "_id": "5aa1bc4db63d79e54e7da545",
        "name": "NIMAIMA",
        "department": "5aa1ac66b63d79e54e7da2e1",
        "dane_dept": "25",
        "dane_town": "25489000",
        "tcc_code": "1613",
        "department_name": "CUNDINAMARCA"
    },
    {
        "_id": "5aa1bc4db63d79e54e7da546",
        "name": "NOCAIMA",
        "department": "5aa1ac66b63d79e54e7da2e1",
        "dane_dept": "25",
        "dane_town": "25491000",
        "tcc_code": "707",
        "department_name": "CUNDINAMARCA"
    },
    {
        "_id": "5aa1bc4db63d79e54e7da549",
        "name": "PANDI",
        "department": "5aa1ac66b63d79e54e7da2e1",
        "dane_dept": "25",
        "dane_town": "25524000",
        "tcc_code": "1034",
        "department_name": "CUNDINAMARCA"
    },
    {
        "_id": "5aa1bc4db63d79e54e7da54b",
        "name": "PASCA",
        "department": "5aa1ac66b63d79e54e7da2e1",
        "dane_dept": "25",
        "dane_town": "25535000",
        "tcc_code": "579",
        "department_name": "CUNDINAMARCA"
    },
    {
        "_id": "5aa1bc4db63d79e54e7da553",
        "name": "SAN BERNARDO",
        "department": "5aa1ac66b63d79e54e7da2e1",
        "dane_dept": "25",
        "dane_town": "25649000",
        "tcc_code": "753",
        "department_name": "CUNDINAMARCA"
    },
    {
        "_id": "5aa1bc4eb63d79e54e7da557",
        "name": "SASAIMA",
        "department": "5aa1ac66b63d79e54e7da2e1",
        "dane_dept": "25",
        "dane_town": "25718000",
        "tcc_code": "392",
        "department_name": "CUNDINAMARCA"
    },
    {
        "_id": "5aa1bc4eb63d79e54e7da558",
        "name": "SESQUILÉ",
        "department": "5aa1ac66b63d79e54e7da2e1",
        "dane_dept": "25",
        "dane_town": "25736000",
        "tcc_code": "394",
        "department_name": "CUNDINAMARCA"
    },
    {
        "_id": "5aa1bc4eb63d79e54e7da559",
        "name": "SIBATÉ",
        "department": "5aa1ac66b63d79e54e7da2e1",
        "dane_dept": "25",
        "dane_town": "25740000",
        "tcc_code": "396",
        "department_name": "CUNDINAMARCA"
    },
    {
        "_id": "5aa1bc4eb63d79e54e7da55a",
        "name": "SILVANIA",
        "department": "5aa1ac66b63d79e54e7da2e1",
        "dane_dept": "25",
        "dane_town": "25743000",
        "tcc_code": "580",
        "department_name": "CUNDINAMARCA"
    },
    {
        "_id": "5aa1bc4eb63d79e54e7da55b",
        "name": "SIMIJACA",
        "department": "5aa1ac66b63d79e54e7da2e1",
        "dane_dept": "25",
        "dane_town": "25745000",
        "tcc_code": "397",
        "department_name": "CUNDINAMARCA"
    },
    {
        "_id": "5aa1bc4eb63d79e54e7da55c",
        "name": "SOACHA",
        "department": "5aa1ac66b63d79e54e7da2e1",
        "dane_dept": "25",
        "dane_town": "25754000",
        "tcc_code": "399",
        "department_name": "CUNDINAMARCA"
    },
    {
        "_id": "5aa1bc4eb63d79e54e7da55d",
        "name": "SOPÓ",
        "department": "5aa1ac66b63d79e54e7da2e1",
        "dane_dept": "25",
        "dane_town": "25758000",
        "tcc_code": "406",
        "department_name": "CUNDINAMARCA"
    },
    {
        "_id": "5aa1bc4eb63d79e54e7da55e",
        "name": "SUBACHOQUE",
        "department": "5aa1ac66b63d79e54e7da2e1",
        "dane_dept": "25",
        "dane_town": "25769000",
        "tcc_code": "546",
        "department_name": "CUNDINAMARCA"
    },
    {
        "_id": "5aa1bc4eb63d79e54e7da55f",
        "name": "SUESCA",
        "department": "5aa1ac66b63d79e54e7da2e1",
        "dane_dept": "25",
        "dane_town": "25772000",
        "tcc_code": "659",
        "department_name": "CUNDINAMARCA"
    },
    {
        "_id": "5aa1bc4eb63d79e54e7da561",
        "name": "SUSA",
        "department": "5aa1ac66b63d79e54e7da2e1",
        "dane_dept": "25",
        "dane_town": "25779000",
        "tcc_code": "865",
        "department_name": "CUNDINAMARCA"
    },
    {
        "_id": "5aa1bc4eb63d79e54e7da562",
        "name": "SUTATAUSA",
        "department": "5aa1ac66b63d79e54e7da2e1",
        "dane_dept": "25",
        "dane_town": "25781000",
        "tcc_code": "1694",
        "department_name": "CUNDINAMARCA"
    },
    {
        "_id": "5aa1bc4eb63d79e54e7da563",
        "name": "TABIO",
        "department": "5aa1ac66b63d79e54e7da2e1",
        "dane_dept": "25",
        "dane_town": "25785000",
        "tcc_code": "410",
        "department_name": "CUNDINAMARCA"
    },
    {
        "_id": "5aa1bc4eb63d79e54e7da564",
        "name": "TAUSA",
        "department": "5aa1ac66b63d79e54e7da2e1",
        "dane_dept": "25",
        "dane_town": "25793000",
        "tcc_code": "1098",
        "department_name": "CUNDINAMARCA"
    },
    {
        "_id": "5aa1bc4eb63d79e54e7da565",
        "name": "TENA",
        "department": "5aa1ac66b63d79e54e7da2e1",
        "dane_dept": "25",
        "dane_town": "25797000",
        "tcc_code": "1122",
        "department_name": "CUNDINAMARCA"
    },
    {
        "_id": "5aa1bc4eb63d79e54e7da566",
        "name": "TENJO",
        "department": "5aa1ac66b63d79e54e7da2e1",
        "dane_dept": "25",
        "dane_town": "25799000",
        "tcc_code": "477",
        "department_name": "CUNDINAMARCA"
    },
    {
        "_id": "5aa1bc4eb63d79e54e7da569",
        "name": "TOCAIMA",
        "department": "5aa1ac66b63d79e54e7da2e1",
        "dane_dept": "25",
        "dane_town": "25815000",
        "tcc_code": "423",
        "department_name": "CUNDINAMARCA"
    },
    {
        "_id": "5aa1bc4eb63d79e54e7da56a",
        "name": "TOCANCIPÁ",
        "department": "5aa1ac66b63d79e54e7da2e1",
        "dane_dept": "25",
        "dane_town": "25817000",
        "tcc_code": "482",
        "department_name": "CUNDINAMARCA"
    },
    {
        "_id": "5aa1bc4eb63d79e54e7da575",
        "name": "VILLAPINZÓN",
        "department": "5aa1ac66b63d79e54e7da2e1",
        "dane_dept": "25",
        "dane_town": "25873000",
        "tcc_code": "450",
        "department_name": "CUNDINAMARCA"
    },
    {
        "_id": "5aa1bc4eb63d79e54e7da576",
        "name": "VILLETA",
        "department": "5aa1ac66b63d79e54e7da2e1",
        "dane_dept": "25",
        "dane_town": "25875000",
        "tcc_code": "452",
        "department_name": "CUNDINAMARCA"
    },
    {
        "_id": "5aa1bc4eb63d79e54e7da577",
        "name": "VIOTÁ",
        "department": "5aa1ac66b63d79e54e7da2e1",
        "dane_dept": "25",
        "dane_town": "25878000",
        "tcc_code": "453",
        "department_name": "CUNDINAMARCA"
    },
    {
        "_id": "5aa1bc4eb63d79e54e7da579",
        "name": "ZIPACÓN",
        "department": "5aa1ac66b63d79e54e7da2e1",
        "dane_dept": "25",
        "dane_town": "25898000",
        "tcc_code": "1629",
        "department_name": "CUNDINAMARCA"
    },
    {
        "_id": "5aa1bc4eb63d79e54e7da57a",
        "name": "ZIPAQUIRÁ",
        "department": "5aa1ac66b63d79e54e7da2e1",
        "dane_dept": "25",
        "dane_town": "25899000",
        "tcc_code": "464",
        "department_name": "CUNDINAMARCA"
    },
    {
        "_id": "5aa1bc4eb63d79e54e7da58a",
        "name": "AIPE",
        "department": "5aa1ac66b63d79e54e7da2e4",
        "dane_dept": "41",
        "dane_town": "41016000",
        "tcc_code": "501",
        "department_name": "HUILA"
    },
    {
        "_id": "5aa1bc4fb63d79e54e7da59a",
        "name": "NEIVA",
        "department": "5aa1ac66b63d79e54e7da2e4",
        "dane_dept": "41",
        "dane_town": "41001000",
        "tcc_code": "13",
        "department_name": "HUILA"
    },
    {
        "_id": "5aa1bc4fb63d79e54e7da5b5",
        "name": "MAICAO",
        "department": "5aa1ac66b63d79e54e7da2e5",
        "dane_dept": "44",
        "dane_town": "44430000",
        "tcc_code": "241",
        "department_name": "LA GUAJIRA"
    },
    {
        "_id": "5aa1bc4fb63d79e54e7da5b7",
        "name": "RIOHACHA",
        "department": "5aa1ac66b63d79e54e7da2e5",
        "dane_dept": "44",
        "dane_town": "44001000",
        "tcc_code": "326",
        "department_name": "LA GUAJIRA"
    },
    {
        "_id": "5aa1bc4fb63d79e54e7da5bc",
        "name": "ALGARROBO",
        "department": "5aa1ac66b63d79e54e7da2e6",
        "dane_dept": "47",
        "dane_town": "47030000",
        "tcc_code": "778",
        "department_name": "MAGDALENA"
    },
    {
        "_id": "5aa1bc4fb63d79e54e7da5bd",
        "name": "ARACATACA",
        "department": "5aa1ac66b63d79e54e7da2e6",
        "dane_dept": "47",
        "dane_town": "47053000",
        "tcc_code": "33",
        "department_name": "MAGDALENA"
    },
    {
        "_id": "5aa1bc4fb63d79e54e7da5c1",
        "name": "CIÉNAGA",
        "department": "5aa1ac66b63d79e54e7da2e6",
        "dane_dept": "47",
        "dane_town": "47189000",
        "tcc_code": "116",
        "department_name": "MAGDALENA"
    },
    {
        "_id": "5aa1bc4fb63d79e54e7da5c5",
        "name": "EL RETÉN",
        "department": "5aa1ac66b63d79e54e7da2e6",
        "dane_dept": "47",
        "dane_town": "47268000",
        "tcc_code": "776",
        "department_name": "MAGDALENA"
    },
    {
        "_id": "5aa1bc4fb63d79e54e7da5c6",
        "name": "FUNDACIÓN",
        "department": "5aa1ac66b63d79e54e7da2e6",
        "dane_dept": "47",
        "dane_town": "47288000",
        "tcc_code": "169",
        "department_name": "MAGDALENA"
    },
    {
        "_id": "5aa1bc4fb63d79e54e7da5c7",
        "name": "GUAMAL",
        "department": "5aa1ac66b63d79e54e7da2e6",
        "dane_dept": "47",
        "dane_town": "47318000",
        "tcc_code": "188",
        "department_name": "MAGDALENA"
    },
    {
        "_id": "5aa1bc50b63d79e54e7da5d5",
        "name": "SANTA MARTA",
        "department": "5aa1ac66b63d79e54e7da2e6",
        "dane_dept": "47",
        "dane_town": "47001000",
        "tcc_code": "383",
        "department_name": "MAGDALENA"
    },
    {
        "_id": "5aa1bc50b63d79e54e7da5da",
        "name": "ACACIAS",
        "department": "5aa1ac66b63d79e54e7da2e7",
        "dane_dept": "50",
        "dane_town": "50006000",
        "tcc_code": "733",
        "department_name": "META"
    },
    {
        "_id": "5aa1bc50b63d79e54e7da5dd",
        "name": "CASTILLA LA NUEVA",
        "department": "5aa1ac66b63d79e54e7da2e7",
        "dane_dept": "50",
        "dane_town": "50150000",
        "tcc_code": "1102",
        "department_name": "META"
    },
    {
        "_id": "5aa1bc50b63d79e54e7da5de",
        "name": "CUBARRAL",
        "department": "5aa1ac66b63d79e54e7da2e7",
        "dane_dept": "50",
        "dane_town": "50223000",
        "tcc_code": "893",
        "department_name": "META"
    },
    {
        "_id": "5aa1bc50b63d79e54e7da5e3",
        "name": "FUENTE DE ORO",
        "department": "5aa1ac66b63d79e54e7da2e7",
        "dane_dept": "50",
        "dane_town": "50287000",
        "tcc_code": "168",
        "department_name": "META"
    },
    {
        "_id": "5aa1bc50b63d79e54e7da5ef",
        "name": "RESTREPO",
        "department": "5aa1ac66b63d79e54e7da2e7",
        "dane_dept": "50",
        "dane_town": "50606000",
        "tcc_code": "323",
        "department_name": "META"
    },
    {
        "_id": "5aa1bc50b63d79e54e7da612",
        "name": "IPIALES",
        "department": "5aa1ac66b63d79e54e7da2e8",
        "dane_dept": "52",
        "dane_town": "52356000",
        "tcc_code": "201",
        "department_name": "NARIÑO"
    },
    {
        "_id": "5aa1bc51b63d79e54e7da621",
        "name": "PASTO",
        "department": "5aa1ac66b63d79e54e7da2e8",
        "dane_dept": "52",
        "dane_town": "52001000",
        "tcc_code": "11",
        "department_name": "NARIÑO"
    },
    {
        "_id": "5aa1bc51b63d79e54e7da62d",
        "name": "SAN PABLO",
        "department": "5aa1ac66b63d79e54e7da2e8",
        "dane_dept": "52",
        "dane_town": "52693000",
        "tcc_code": "481",
        "department_name": "NARIÑO"
    },
    {
        "_id": "5aa1bc51b63d79e54e7da640",
        "name": "CÚCUTA",
        "department": "5aa1ac66b63d79e54e7da2e9",
        "dane_dept": "54",
        "dane_town": "54001000",
        "tcc_code": "5",
        "department_name": "NORTE DE SANTANDER"
    },
    {
        "_id": "5aa1bc51b63d79e54e7da64c",
        "name": "LOS PATIOS",
        "department": "5aa1ac66b63d79e54e7da2e9",
        "dane_dept": "54",
        "dane_town": "54405000",
        "tcc_code": "637",
        "department_name": "NORTE DE SANTANDER"
    },
    {
        "_id": "5aa1bc51b63d79e54e7da65e",
        "name": "VILLA DEL ROSARIO",
        "department": "5aa1ac66b63d79e54e7da2e9",
        "dane_dept": "54",
        "dane_town": "54874000",
        "tcc_code": "446",
        "department_name": "NORTE DE SANTANDER"
    },
    {
        "_id": "5aa1bc52b63d79e54e7da66c",
        "name": "ARMENIA",
        "department": "5aa1ac66b63d79e54e7da2eb",
        "dane_dept": "63",
        "dane_town": "63001000",
        "tcc_code": "40",
        "department_name": "QUINDÍO"
    },
    {
        "_id": "5aa1bc52b63d79e54e7da66e",
        "name": "CALARCÁ",
        "department": "5aa1ac66b63d79e54e7da2eb",
        "dane_dept": "63",
        "dane_town": "63130000",
        "tcc_code": "78",
        "department_name": "QUINDÍO"
    },
    {
        "_id": "5aa1bc52b63d79e54e7da66f",
        "name": "CIRCASIA",
        "department": "5aa1ac66b63d79e54e7da2eb",
        "dane_dept": "63",
        "dane_town": "63190000",
        "tcc_code": "118",
        "department_name": "QUINDÍO"
    },
    {
        "_id": "5aa1bc52b63d79e54e7da673",
        "name": "LA TEBAIDA",
        "department": "5aa1ac66b63d79e54e7da2eb",
        "dane_dept": "63",
        "dane_town": "63401000",
        "tcc_code": "223",
        "department_name": "QUINDÍO"
    },
    {
        "_id": "5aa1bc52b63d79e54e7da67b",
        "name": "DOSQUEBRADAS",
        "department": "5aa1ac66b63d79e54e7da2ec",
        "dane_dept": "66",
        "dane_town": "66170000",
        "tcc_code": "140",
        "department_name": "RISARALDA"
    },
    {
        "_id": "5aa1bc52b63d79e54e7da681",
        "name": "PEREIRA",
        "department": "5aa1ac66b63d79e54e7da2ec",
        "dane_dept": "66",
        "dane_town": "66001000",
        "tcc_code": "2",
        "department_name": "RISARALDA"
    },
    {
        "_id": "5aa1bc52b63d79e54e7da68e",
        "name": "BUCARAMANGA",
        "department": "5aa1ac66b63d79e54e7da2ed",
        "dane_dept": "68",
        "dane_town": "68001000",
        "tcc_code": "6",
        "department_name": "SANTANDER"
    },
    {
        "_id": "5aa1bc52b63d79e54e7da699",
        "name": "CIMITARRA",
        "department": "5aa1ac66b63d79e54e7da2ed",
        "dane_dept": "68",
        "dane_town": "68190000",
        "tcc_code": "117",
        "department_name": "SANTANDER"
    },
    {
        "_id": "5aa1bc53b63d79e54e7da6a6",
        "name": "FLORIDABLANCA",
        "department": "5aa1ac66b63d79e54e7da2ed",
        "dane_dept": "68",
        "dane_town": "68276000",
        "tcc_code": "162",
        "department_name": "SANTANDER"
    },
    {
        "_id": "5aa1bc53b63d79e54e7da6a9",
        "name": "GIRÓN",
        "department": "5aa1ac66b63d79e54e7da2ed",
        "dane_dept": "68",
        "dane_town": "68307000",
        "tcc_code": "181",
        "department_name": "SANTANDER"
    },
    {
        "_id": "5aa1bc53b63d79e54e7da6b4",
        "name": "LANDÁZURI",
        "department": "5aa1ac66b63d79e54e7da2ed",
        "dane_dept": "68",
        "dane_town": "68385000",
        "tcc_code": "232",
        "department_name": "SANTANDER"
    },
    {
        "_id": "5aa1bc53b63d79e54e7da6c2",
        "name": "PIEDECUESTA",
        "department": "5aa1ac66b63d79e54e7da2ed",
        "dane_dept": "68",
        "dane_town": "68547000",
        "tcc_code": "286",
        "department_name": "SANTANDER"
    },
    {
        "_id": "5aa1bc53b63d79e54e7da6c4",
        "name": "PUENTE NACIONAL",
        "department": "5aa1ac66b63d79e54e7da2ed",
        "dane_dept": "68",
        "dane_town": "68572000",
        "tcc_code": "314",
        "department_name": "SANTANDER"
    },
    {
        "_id": "5aa1bc53b63d79e54e7da6cb",
        "name": "SAN GIL",
        "department": "5aa1ac66b63d79e54e7da2ed",
        "dane_dept": "68",
        "dane_town": "68679000",
        "tcc_code": "358",
        "department_name": "SANTANDER"
    },
    {
        "_id": "5aa1bc53b63d79e54e7da6d3",
        "name": "SOCORRO",
        "department": "5aa1ac66b63d79e54e7da2ed",
        "dane_dept": "68",
        "dane_town": "68755000",
        "tcc_code": "401",
        "department_name": "SANTANDER"
    },
    {
        "_id": "5aa1bc53b63d79e54e7da6d9",
        "name": "VÉLEZ",
        "department": "5aa1ac66b63d79e54e7da2ed",
        "dane_dept": "68",
        "dane_town": "68861000",
        "tcc_code": "439",
        "department_name": "SANTANDER"
    },
    {
        "_id": "5aa1bc53b63d79e54e7da6e1",
        "name": "COROZAL",
        "department": "5aa1ac66b63d79e54e7da2ee",
        "dane_dept": "70",
        "dane_town": "70215000",
        "tcc_code": "129",
        "department_name": "SUCRE"
    },
    {
        "_id": "5aa1bc54b63d79e54e7da6e2",
        "name": "COVEÑAS",
        "department": "5aa1ac66b63d79e54e7da2ee",
        "dane_dept": "70",
        "dane_town": "70221000",
        "tcc_code": "130",
        "department_name": "SUCRE"
    },
    {
        "_id": "5aa1bc54b63d79e54e7da6f0",
        "name": "SAN MARCOS",
        "department": "5aa1ac66b63d79e54e7da2ee",
        "dane_dept": "70",
        "dane_town": "70708000",
        "tcc_code": "367",
        "department_name": "SUCRE"
    },
    {
        "_id": "5aa1bc54b63d79e54e7da6f4",
        "name": "SINCELEJO",
        "department": "5aa1ac66b63d79e54e7da2ee",
        "dane_dept": "70",
        "dane_town": "70001000",
        "tcc_code": "14",
        "department_name": "SUCRE"
    },
    {
        "_id": "5aa1bc54b63d79e54e7da6f6",
        "name": "TOLÚ VIEJO",
        "department": "5aa1ac66b63d79e54e7da2ee",
        "dane_dept": "70",
        "dane_town": "70823000",
        "tcc_code": "519",
        "department_name": "SUCRE"
    },
    {
        "_id": "5aa1bc54b63d79e54e7da6fe",
        "name": "CARMEN DE APICALA",
        "department": "5aa1ac66b63d79e54e7da2ef",
        "dane_dept": "73",
        "dane_town": "73148000",
        "tcc_code": "581",
        "department_name": "TOLIMA"
    },
    {
        "_id": "5aa1bc54b63d79e54e7da70c",
        "name": "IBAGUÉ",
        "department": "5aa1ac66b63d79e54e7da2ef",
        "dane_dept": "73",
        "dane_town": "73001000",
        "tcc_code": "9",
        "department_name": "TOLIMA"
    },
    {
        "_id": "5aa1bc54b63d79e54e7da70d",
        "name": "ICONONZO",
        "department": "5aa1ac66b63d79e54e7da2ef",
        "dane_dept": "73",
        "dane_town": "73352000",
        "tcc_code": "534",
        "department_name": "TOLIMA"
    },
    {
        "_id": "5aa1bc54b63d79e54e7da711",
        "name": "MELGAR",
        "department": "5aa1ac66b63d79e54e7da2ef",
        "dane_dept": "73",
        "dane_town": "73449000",
        "tcc_code": "252",
        "department_name": "TOLIMA"
    },
    {
        "_id": "5aa1bc54b63d79e54e7da71e",
        "name": "SAN ANTONIO",
        "department": "5aa1ac66b63d79e54e7da2ef",
        "dane_dept": "73",
        "dane_town": "73675000",
        "tcc_code": "351",
        "department_name": "TOLIMA"
    },
    {
        "_id": "5aa1bc54b63d79e54e7da727",
        "name": "ANDALUCÍA",
        "department": "5aa1ac66b63d79e54e7da2f0",
        "dane_dept": "76",
        "dane_town": "76036000",
        "tcc_code": "28",
        "department_name": "VALLE DEL CAUCA"
    },
    {
        "_id": "5aa1bc55b63d79e54e7da72b",
        "name": "BUENAVENTURA",
        "department": "5aa1ac66b63d79e54e7da2f0",
        "dane_dept": "76",
        "dane_town": "76109000",
        "tcc_code": "68",
        "department_name": "VALLE DEL CAUCA"
    },
    {
        "_id": "5aa1bc55b63d79e54e7da72c",
        "name": "BUGALAGRANDE",
        "department": "5aa1ac66b63d79e54e7da2f0",
        "dane_dept": "76",
        "dane_town": "76113000",
        "tcc_code": "72",
        "department_name": "VALLE DEL CAUCA"
    },
    {
        "_id": "5aa1bc55b63d79e54e7da72e",
        "name": "CALI",
        "department": "5aa1ac66b63d79e54e7da2f0",
        "dane_dept": "76",
        "dane_town": "76001000",
        "tcc_code": "3",
        "department_name": "VALLE DEL CAUCA"
    },
    {
        "_id": "5aa1bc55b63d79e54e7da731",
        "name": "CARTAGO",
        "department": "5aa1ac66b63d79e54e7da2f0",
        "dane_dept": "76",
        "dane_town": "76147000",
        "tcc_code": "94",
        "department_name": "VALLE DEL CAUCA"
    },
    {
        "_id": "5aa1bc55b63d79e54e7da732",
        "name": "DAGUA",
        "department": "5aa1ac66b63d79e54e7da2f0",
        "dane_dept": "76",
        "dane_town": "76233000",
        "tcc_code": "136",
        "department_name": "VALLE DEL CAUCA"
    },
    {
        "_id": "5aa1bc55b63d79e54e7da735",
        "name": "EL CERRITO",
        "department": "5aa1ac66b63d79e54e7da2f0",
        "dane_dept": "76",
        "dane_town": "76248000",
        "tcc_code": "99",
        "department_name": "VALLE DEL CAUCA"
    },
    {
        "_id": "5aa1bc55b63d79e54e7da737",
        "name": "FLORIDA",
        "department": "5aa1ac66b63d79e54e7da2f0",
        "dane_dept": "76",
        "dane_town": "76275000",
        "tcc_code": "161",
        "department_name": "VALLE DEL CAUCA"
    },
    {
        "_id": "5aa1bc55b63d79e54e7da738",
        "name": "GINEBRA",
        "department": "5aa1ac66b63d79e54e7da2f0",
        "dane_dept": "76",
        "dane_town": "76306000",
        "tcc_code": "178",
        "department_name": "VALLE DEL CAUCA"
    },
    {
        "_id": "5aa1bc55b63d79e54e7da739",
        "name": "GUACARÍ",
        "department": "5aa1ac66b63d79e54e7da2f0",
        "dane_dept": "76",
        "dane_town": "76318000",
        "tcc_code": "185",
        "department_name": "VALLE DEL CAUCA"
    },
    {
        "_id": "5aa1bc55b63d79e54e7da73a",
        "name": "GUADALAJARA DE BUGA",
        "department": "5aa1ac66b63d79e54e7da2f0",
        "dane_dept": "76",
        "dane_town": "76111000",
        "tcc_code": "71",
        "department_name": "VALLE DEL CAUCA"
    },
    {
        "_id": "5aa1bc55b63d79e54e7da73b",
        "name": "JAMUNDÍ",
        "department": "5aa1ac66b63d79e54e7da2f0",
        "dane_dept": "76",
        "dane_town": "76364000",
        "tcc_code": "203",
        "department_name": "VALLE DEL CAUCA"
    },
    {
        "_id": "5aa1bc55b63d79e54e7da73c",
        "name": "LA CUMBRE",
        "department": "5aa1ac66b63d79e54e7da2f0",
        "dane_dept": "76",
        "dane_town": "76377000",
        "tcc_code": "558",
        "department_name": "VALLE DEL CAUCA"
    },
    {
        "_id": "5aa1bc55b63d79e54e7da740",
        "name": "PALMIRA",
        "department": "5aa1ac66b63d79e54e7da2f0",
        "dane_dept": "76",
        "dane_town": "76520000",
        "tcc_code": "280",
        "department_name": "VALLE DEL CAUCA"
    },
    {
        "_id": "5aa1bc55b63d79e54e7da741",
        "name": "PRADERA",
        "department": "5aa1ac66b63d79e54e7da2f0",
        "dane_dept": "76",
        "dane_town": "76563000",
        "tcc_code": "295",
        "department_name": "VALLE DEL CAUCA"
    },
    {
        "_id": "5aa1bc55b63d79e54e7da743",
        "name": "RIOFRÍO",
        "department": "5aa1ac66b63d79e54e7da2f0",
        "dane_dept": "76",
        "dane_town": "76616000",
        "tcc_code": "723",
        "department_name": "VALLE DEL CAUCA"
    },
    {
        "_id": "5aa1bc55b63d79e54e7da746",
        "name": "SEVILLA",
        "department": "5aa1ac66b63d79e54e7da2f0",
        "dane_dept": "76",
        "dane_town": "76736000",
        "tcc_code": "395",
        "department_name": "VALLE DEL CAUCA"
    },
    {
        "_id": "5aa1bc55b63d79e54e7da748",
        "name": "TRUJILLO",
        "department": "5aa1ac66b63d79e54e7da2f0",
        "dane_dept": "76",
        "dane_town": "76828000",
        "tcc_code": "426",
        "department_name": "VALLE DEL CAUCA"
    },
    {
        "_id": "5aa1bc55b63d79e54e7da749",
        "name": "TULUÁ",
        "department": "5aa1ac66b63d79e54e7da2f0",
        "dane_dept": "76",
        "dane_town": "76834000",
        "tcc_code": "427",
        "department_name": "VALLE DEL CAUCA"
    },
    {
        "_id": "5aa1bc55b63d79e54e7da74c",
        "name": "VIJES",
        "department": "5aa1ac66b63d79e54e7da2f0",
        "dane_dept": "76",
        "dane_town": "76869000",
        "tcc_code": "445",
        "department_name": "VALLE DEL CAUCA"
    },
    {
        "_id": "5aa1bc55b63d79e54e7da74d",
        "name": "YOTOCO",
        "department": "5aa1ac66b63d79e54e7da2f0",
        "dane_dept": "76",
        "dane_town": "76890000",
        "tcc_code": "557",
        "department_name": "VALLE DEL CAUCA"
    },
    {
        "_id": "5aa1bc55b63d79e54e7da74e",
        "name": "YUMBO",
        "department": "5aa1ac66b63d79e54e7da2f0",
        "dane_dept": "76",
        "dane_town": "76892000",
        "tcc_code": "459",
        "department_name": "VALLE DEL CAUCA"
    },
    {
        "_id": "5b9ffd696cbf7552d56fa5da",
        "name": "PALERMO",
        "department": "5aa1ac66b63d79e54e7da2e4",
        "dane_dept": "41",
        "dane_town": "41524000",
        "tcc_code": "278",
        "department_name": "HUILA"
    }
]